comdutils
