Metadata-Version: 1.0
Name: comdutils
Version: 0.3.3
Summary: a simple package for computer vision deployment
Home-page: UNKNOWN
Author: fatchur rahman
Author-email: UNKNOWN
License: UNKNOWN
Platform: UNKNOWN
